{"map": {"connections": [{"a": 30002384, "b": 30002383, "y2": "149.5", "x2": "28.5", "y1": "99.5", "x1": "28.5", "type": "j"}, {"a": 30002385, "b": 30002383, "y2": "134.5", "x2": "108.5", "y1": "99.5", "x1": "28.5", "type": "j"}, {"a": 30002523, "b": 30002383, "y2": "49.5", "x2": "28.5", "y1": "99.5", "x1": "28.5", "type": "jr"}, {"a": 30002385, "b": 30002384, "y2": "134.5", "x2": "108.5", "y1": "149.5", "x1": "28.5", "type": "j"}, {"a": 30002386, "b": 30002385, "y2": "84.5", "x2": "193.5", "y1": "134.5", "x1": "108.5", "type": "j"}, {"a": 30002387, "b": 30002385, "y2": "179.5", "x2": "168.5", "y1": "134.5", "x1": "108.5", "type": "j"}, {"a": 30002570, "b": 30002385, "y2": "59.5", "x2": "103.5", "y1": "134.5", "x1": "108.5", "type": "jr"}, {"a": 30002388, "b": 30002386, "y2": "129.5", "x2": "243.5", "y1": "84.5", "x1": "193.5", "type": "j"}, {"a": 30002389, "b": 30002386, "y2": "104.5", "x2": "338.5", "y1": "84.5", "x1": "193.5", "type": "j"}, {"a": 30002388, "b": 30002387, "y2": "129.5", "x2": "243.5", "y1": "179.5", "x1": "168.5", "type": "j"}, {"a": 30002390, "b": 30002387, "y2": "434.5", "x2": "138.5", "y1": "179.5", "x1": "168.5", "type": "jc"}, {"a": 30002389, "b": 30002388, "y2": "104.5", "x2": "338.5", "y1": "129.5", "x1": "243.5", "type": "j"}, {"a": 30002402, "b": 30002388, "y2": "229.5", "x2": "293.5", "y1": "129.5", "x1": "243.5", "type": "jc"}, {"a": 30002396, "b": 30002389, "y2": "99.5", "x2": "433.5", "y1": "104.5", "x1": "338.5", "type": "jc"}, {"a": 30002391, "b": 30002390, "y2": "464.5", "x2": "78.5", "y1": "434.5", "x1": "138.5", "type": "j"}, {"a": 30002393, "b": 30002390, "y2": "484.5", "x2": "178.5", "y1": "434.5", "x1": "138.5", "type": "j"}, {"a": 30002392, "b": 30002391, "y2": "499.5", "x2": "28.5", "y1": "464.5", "x1": "78.5", "type": "j"}, {"a": 30002394, "b": 30002393, "y2": "514.5", "x2": "253.5", "y1": "484.5", "x1": "178.5", "type": "j"}, {"a": 30002395, "b": 30002393, "y2": "529.5", "x2": "153.5", "y1": "484.5", "x1": "178.5", "type": "j"}, {"a": 30002420, "b": 30002394, "y2": "574.5", "x2": "548.5", "y1": "514.5", "x1": "253.5", "type": "jc"}, {"a": 30002395, "b": 30000116, "y2": "574.5", "x2": "108.5", "y1": "529.5", "x1": "153.5", "type": "jr"}, {"a": 30002397, "b": 30002396, "y2": "119.5", "x2": "528.5", "y1": "99.5", "x1": "433.5", "type": "j"}, {"a": 30002401, "b": 30002396, "y2": "69.5", "x2": "563.5", "y1": "99.5", "x1": "433.5", "type": "j"}, {"a": 30002398, "b": 30002397, "y2": "179.5", "x2": "538.5", "y1": "119.5", "x1": "528.5", "type": "j"}, {"a": 30002399, "b": 30002397, "y2": "149.5", "x2": "633.5", "y1": "119.5", "x1": "528.5", "type": "j"}, {"a": 30002400, "b": 30002397, "y2": "159.5", "x2": "453.5", "y1": "119.5", "x1": "528.5", "type": "j"}, {"a": 30002400, "b": 30002398, "y2": "159.5", "x2": "453.5", "y1": "179.5", "x1": "538.5", "type": "j"}, {"a": 30002401, "b": 30002399, "y2": "69.5", "x2": "563.5", "y1": "149.5", "x1": "633.5", "type": "j"}, {"a": 30002408, "b": 30002399, "y2": "199.5", "x2": "748.5", "y1": "149.5", "x1": "633.5", "type": "jc"}, {"a": 30002412, "b": 30002401, "y2": "64.5", "x2": "688.5", "y1": "69.5", "x1": "563.5", "type": "jc"}, {"a": 30002403, "b": 30002402, "y2": "274.5", "x2": "258.5", "y1": "229.5", "x1": "293.5", "type": "j"}, {"a": 30002404, "b": 30002402, "y2": "274.5", "x2": "328.5", "y1": "229.5", "x1": "293.5", "type": "j"}, {"a": 30002407, "b": 30002402, "y2": "229.5", "x2": "378.5", "y1": "229.5", "x1": "293.5", "type": "j"}, {"a": 30002404, "b": 30002403, "y2": "274.5", "x2": "328.5", "y1": "274.5", "x1": "258.5", "type": "j"}, {"a": 30002406, "b": 30002403, "y2": "319.5", "x2": "258.5", "y1": "274.5", "x1": "258.5", "type": "j"}, {"a": 30002405, "b": 30002404, "y2": "319.5", "x2": "333.5", "y1": "274.5", "x1": "328.5", "type": "j"}, {"a": 30002409, "b": 30002408, "y2": "249.5", "x2": "808.5", "y1": "199.5", "x1": "748.5", "type": "j"}, {"a": 30002410, "b": 30002408, "y2": "169.5", "x2": "858.5", "y1": "199.5", "x1": "748.5", "type": "j"}, {"a": 30002410, "b": 30002409, "y2": "169.5", "x2": "858.5", "y1": "249.5", "x1": "808.5", "type": "j"}, {"a": 30002413, "b": 30002409, "y2": "339.5", "x2": "818.5", "y1": "249.5", "x1": "808.5", "type": "j"}, {"a": 30002411, "b": 30002410, "y2": "114.5", "x2": "813.5", "y1": "169.5", "x1": "858.5", "type": "j"}, {"a": 30002411, "b": 30002376, "y2": "84.5", "x2": "883.5", "y1": "114.5", "x1": "813.5", "type": "jr"}, {"a": 30002412, "b": 30002411, "y2": "64.5", "x2": "688.5", "y1": "114.5", "x1": "813.5", "type": "j"}, {"a": 30003465, "b": 30002412, "y2": "34.5", "x2": "758.5", "y1": "64.5", "x1": "688.5", "type": "jr"}, {"a": 30002414, "b": 30002413, "y2": "469.5", "x2": "773.5", "y1": "339.5", "x1": "818.5", "type": "jc"}, {"a": 30002415, "b": 30002414, "y2": "524.5", "x2": "728.5", "y1": "469.5", "x1": "773.5", "type": "j"}, {"a": 30002416, "b": 30002415, "y2": "599.5", "x2": "778.5", "y1": "524.5", "x1": "728.5", "type": "j"}, {"a": 30002419, "b": 30002415, "y2": "564.5", "x2": "638.5", "y1": "524.5", "x1": "728.5", "type": "j"}, {"a": 30002417, "b": 30002416, "y2": "599.5", "x2": "703.5", "y1": "599.5", "x1": "778.5", "type": "j"}, {"a": 30002418, "b": 30002416, "y2": "649.5", "x2": "678.5", "y1": "599.5", "x1": "778.5", "type": "j"}, {"a": 30002418, "b": 30002417, "y2": "649.5", "x2": "678.5", "y1": "599.5", "x1": "703.5", "type": "j"}, {"a": 30002419, "b": 30002417, "y2": "564.5", "x2": "638.5", "y1": "599.5", "x1": "703.5", "type": "j"}, {"a": 30002419, "b": 30002418, "y2": "564.5", "x2": "638.5", "y1": "649.5", "x1": "678.5", "type": "j"}, {"a": 30002420, "b": 30002419, "y2": "574.5", "x2": "548.5", "y1": "564.5", "x1": "638.5", "type": "j"}, {"a": 30002420, "b": 30000970, "y2": "664.5", "x2": "523.5", "y1": "574.5", "x1": "548.5", "type": "jr"}], "bridges": [], "systems": [{"name": "Aeddin", "hasStation": true, "region": "", "y": "85", "x": "0", "id": 30002383}, {"name": "Gulfonodi", "hasStation": true, "region": "", "y": "135", "x": "0", "id": 30002384}, {"name": "Hrober", "hasStation": true, "region": "", "y": "485", "x": "0", "id": 30002392}, {"name": "Hrokkur", "hasStation": true, "region": "", "y": "450", "x": "50", "id": 30002391}, {"name": "Teonusude", "hasStation": true, "region": "", "y": "120", "x": "80", "id": 30002385}, {"name": "Heild", "hasStation": true, "region": "", "y": "420", "x": "110", "id": 30002390}, {"name": "Audesder", "hasStation": false, "region": "", "y": "515", "x": "125", "id": 30002395}, {"name": "Bosena", "hasStation": true, "region": "", "y": "165", "x": "140", "id": 30002387}, {"name": "Aedald", "hasStation": true, "region": "", "y": "470", "x": "150", "id": 30002393}, {"name": "Gelfiven", "hasStation": true, "region": "", "y": "70", "x": "165", "id": 30002386}, {"name": "Oddelulf", "hasStation": true, "region": "", "y": "115", "x": "215", "id": 30002388}, {"name": "Muttokon", "hasStation": false, "region": "", "y": "500", "x": "225", "id": 30002394}, {"name": "Gonheim", "hasStation": false, "region": "", "y": "260", "x": "230", "id": 30002403}, {"name": "Hedaleolfarber", "hasStation": true, "region": "", "y": "305", "x": "230", "id": 30002406}, {"name": "Istodard", "hasStation": true, "region": "", "y": "215", "x": "265", "id": 30002402}, {"name": "Half", "hasStation": true, "region": "", "y": "260", "x": "300", "id": 30002404}, {"name": "Sakulda", "hasStation": true, "region": "", "y": "305", "x": "305", "id": 30002405}, {"name": "Atlar", "hasStation": true, "region": "", "y": "90", "x": "310", "id": 30002389}, {"name": "Altbrard", "hasStation": true, "region": "", "y": "215", "x": "350", "id": 30002407}, {"name": "Illamur", "hasStation": true, "region": "", "y": "85", "x": "405", "id": 30002396}, {"name": "Varigne", "hasStation": false, "region": "", "y": "145", "x": "425", "id": 30002400}, {"name": "Horaka", "hasStation": true, "region": "", "y": "105", "x": "500", "id": 30002397}, {"name": "Eldulf", "hasStation": true, "region": "", "y": "165", "x": "510", "id": 30002398}, {"name": "Egbinger", "hasStation": true, "region": "", "y": "560", "x": "520", "id": 30002420}, {"name": "Meildolf", "hasStation": false, "region": "", "y": "55", "x": "535", "id": 30002401}, {"name": "Orien", "hasStation": true, "region": "", "y": "135", "x": "605", "id": 30002399}, {"name": "Aeditide", "hasStation": true, "region": "", "y": "550", "x": "610", "id": 30002419}, {"name": "Hegfunden", "hasStation": true, "region": "", "y": "635", "x": "650", "id": 30002418}, {"name": "Ennur", "hasStation": true, "region": "", "y": "50", "x": "660", "id": 30002412}, {"name": "Kadlina", "hasStation": false, "region": "", "y": "585", "x": "675", "id": 30002417}, {"name": "Weld", "hasStation": true, "region": "", "y": "510", "x": "700", "id": 30002415}, {"name": "Fegomenko", "hasStation": false, "region": "", "y": "185", "x": "720", "id": 30002408}, {"name": "Klingt", "hasStation": true, "region": "", "y": "455", "x": "745", "id": 30002414}, {"name": "Kattegaud", "hasStation": false, "region": "", "y": "585", "x": "750", "id": 30002416}, {"name": "Osvetur", "hasStation": false, "region": "", "y": "235", "x": "780", "id": 30002409}, {"name": "Skarkon", "hasStation": true, "region": "", "y": "100", "x": "785", "id": 30002411}, {"name": "Unertek", "hasStation": true, "region": "", "y": "325", "x": "790", "id": 30002413}, {"name": "Mimiror", "hasStation": false, "region": "", "y": "155", "x": "830", "id": 30002410}, {"name": "Austraka", "hasStation": false, "region": "Heimatar", "y": "35", "x": "0", "id": 30002523}, {"name": "Magiko", "hasStation": false, "region": "Heimatar", "y": "45", "x": "75", "id": 30002570}, {"name": "Kenobanala", "hasStation": false, "region": "Derelik", "y": "560", "x": "80", "id": 30000116}, {"name": "B-VIP9", "hasStation": false, "region": "Great Wildlands", "y": "650", "x": "495", "id": 30000970}, {"name": "Tabbetzur", "hasStation": true, "region": "Metropolis", "y": "20", "x": "730", "id": 30003465}, {"name": "L4X-1V", "hasStation": false, "region": "Etherium Reach", "y": "70", "x": "855", "id": 30002376}]}}