{"map": {"connections": [{"a": 30000120, "b": 30000119, "y2": "499.5", "x2": "363.5", "y1": "459.5", "x1": "333.5", "type": "j"}, {"a": 30000121, "b": 30000119, "y2": "459.5", "x2": "268.5", "y1": "459.5", "x1": "333.5", "type": "j"}, {"a": 30000123, "b": 30000119, "y2": "494.5", "x2": "293.5", "y1": "459.5", "x1": "333.5", "type": "j"}, {"a": 30000124, "b": 30000119, "y2": "429.5", "x2": "383.5", "y1": "459.5", "x1": "333.5", "type": "j"}, {"a": 30000125, "b": 30000119, "y2": "469.5", "x2": "398.5", "y1": "459.5", "x1": "333.5", "type": "j"}, {"a": 30000140, "b": 30000119, "y2": "417.5", "x2": "254.5", "y1": "459.5", "x1": "333.5", "type": "jc"}, {"a": 30000122, "b": 30000120, "y2": "534.5", "x2": "388.5", "y1": "499.5", "x1": "363.5", "type": "j"}, {"a": 30000128, "b": 30000126, "y2": "654.5", "x2": "333.5", "y1": "659.5", "x1": "438.5", "type": "j"}, {"a": 30000131, "b": 30000126, "y2": "634.5", "x2": "513.5", "y1": "659.5", "x1": "438.5", "type": "j"}, {"a": 30000128, "b": 30000127, "y2": "654.5", "x2": "333.5", "y1": "689.5", "x1": "293.5", "type": "j"}, {"a": 30002788, "b": 30000127, "y2": "679.5", "x2": "128.5", "y1": "689.5", "x1": "293.5", "type": "jr"}, {"a": 30000130, "b": 30000128, "y2": "634.5", "x2": "228.5", "y1": "654.5", "x1": "333.5", "type": "j"}, {"a": 30000130, "b": 30000129, "y2": "634.5", "x2": "228.5", "y1": "589.5", "x1": "163.5", "type": "j"}, {"a": 30000139, "b": 30000129, "y2": "504.5", "x2": "123.5", "y1": "589.5", "x1": "163.5", "type": "jc"}, {"a": 30030141, "b": 30000129, "y2": "559.5", "x2": "228.5", "y1": "589.5", "x1": "163.5", "type": "j"}, {"a": 30020141, "b": 30000130, "y2": "594.5", "x2": "293.5", "y1": "634.5", "x1": "228.5", "type": "j"}, {"a": 30000146, "b": 30000131, "y2": "514.5", "x2": "473.5", "y1": "634.5", "x1": "513.5", "type": "jc"}, {"a": 30000153, "b": 30000131, "y2": "404.5", "x2": "703.5", "y1": "634.5", "x1": "513.5", "type": "jc"}, {"a": 30000133, "b": 30000132, "y2": "257.5", "x2": "162.5", "y1": "243.5", "x1": "94.5", "type": "j"}, {"a": 30000134, "b": 30000132, "y2": "204.5", "x2": "73.5", "y1": "243.5", "x1": "94.5", "type": "j"}, {"a": 30000138, "b": 30000132, "y2": "286.5", "x2": "122.5", "y1": "243.5", "x1": "94.5", "type": "j"}, {"a": 30000138, "b": 30000133, "y2": "286.5", "x2": "122.5", "y1": "257.5", "x1": "162.5", "type": "j"}, {"a": 30000145, "b": 30000133, "y2": "293.5", "x2": "253.5", "y1": "257.5", "x1": "162.5", "type": "jc"}, {"a": 30021407, "b": 30000133, "y2": "219.5", "x2": "173.5", "y1": "257.5", "x1": "162.5", "type": "j"}, {"a": 30000135, "b": 30000134, "y2": "159.5", "x2": "28.5", "y1": "204.5", "x1": "73.5", "type": "j"}, {"a": 30000136, "b": 30000134, "y2": "159.5", "x2": "108.5", "y1": "204.5", "x1": "73.5", "type": "j"}, {"a": 30000136, "b": 30000135, "y2": "159.5", "x2": "108.5", "y1": "159.5", "x1": "28.5", "type": "j"}, {"a": 30000137, "b": 30000135, "y2": "114.5", "x2": "63.5", "y1": "159.5", "x1": "28.5", "type": "j"}, {"a": 30000137, "b": 30000136, "y2": "114.5", "x2": "63.5", "y1": "159.5", "x1": "108.5", "type": "j"}, {"a": 30000142, "b": 30000138, "y2": "357.5", "x2": "252.5", "y1": "286.5", "x1": "122.5", "type": "jc"}, {"a": 30001379, "b": 30000138, "y2": "349.5", "x2": "88.5", "y1": "286.5", "x1": "122.5", "type": "jr"}, {"a": 30010141, "b": 30000138, "y2": "304.5", "x2": "28.5", "y1": "286.5", "x1": "122.5", "type": "j"}, {"a": 30000141, "b": 30000139, "y2": "494.5", "x2": "188.5", "y1": "504.5", "x1": "123.5", "type": "j"}, {"a": 30000144, "b": 30000139, "y2": "394.5", "x2": "174.5", "y1": "504.5", "x1": "123.5", "type": "j"}, {"a": 30002791, "b": 30000139, "y2": "604.5", "x2": "73.5", "y1": "504.5", "x1": "123.5", "type": "jr"}, {"a": 30002802, "b": 30000139, "y2": "479.5", "x2": "53.5", "y1": "504.5", "x1": "123.5", "type": "jr"}, {"a": 30000142, "b": 30000140, "y2": "357.5", "x2": "252.5", "y1": "417.5", "x1": "254.5", "type": "j"}, {"a": 30000144, "b": 30000140, "y2": "394.5", "x2": "174.5", "y1": "417.5", "x1": "254.5", "type": "j"}, {"a": 30002780, "b": 30000140, "y2": "389.5", "x2": "332.5", "y1": "417.5", "x1": "254.5", "type": "jr"}, {"a": 30000143, "b": 30000142, "y2": "341.5", "x2": "175.5", "y1": "357.5", "x1": "252.5", "type": "j"}, {"a": 30000144, "b": 30000142, "y2": "394.5", "x2": "174.5", "y1": "357.5", "x1": "252.5", "type": "j"}, {"a": 30000145, "b": 30000142, "y2": "293.5", "x2": "253.5", "y1": "357.5", "x1": "252.5", "type": "j"}, {"a": 30001363, "b": 30000142, "y2": "349.5", "x2": "334.5", "y1": "357.5", "x1": "252.5", "type": "jr"}, {"a": 30002780, "b": 30000142, "y2": "389.5", "x2": "332.5", "y1": "357.5", "x1": "252.5", "type": "jr"}, {"a": 30000144, "b": 30000143, "y2": "394.5", "x2": "174.5", "y1": "341.5", "x1": "175.5", "type": "j"}, {"a": 30000145, "b": 30000143, "y2": "293.5", "x2": "253.5", "y1": "341.5", "x1": "175.5", "type": "j"}, {"a": 30001379, "b": 30000143, "y2": "349.5", "x2": "88.5", "y1": "341.5", "x1": "175.5", "type": "jr"}, {"a": 30002642, "b": 30000144, "y2": "409.5", "x2": "63.5", "y1": "394.5", "x1": "174.5", "type": "jr"}, {"a": 30000156, "b": 30000145, "y2": "308.5", "x2": "602.5", "y1": "293.5", "x1": "253.5", "type": "jc"}, {"a": 30001393, "b": 30000145, "y2": "314.5", "x2": "330.5", "y1": "293.5", "x1": "253.5", "type": "jr"}, {"a": 30002754, "b": 30000145, "y2": "249.5", "x2": "333.5", "y1": "293.5", "x1": "253.5", "type": "jr"}, {"a": 30000147, "b": 30000146, "y2": "539.5", "x2": "533.5", "y1": "514.5", "x1": "473.5", "type": "j"}, {"a": 30000148, "b": 30000146, "y2": "464.5", "x2": "468.5", "y1": "514.5", "x1": "473.5", "type": "j"}, {"a": 30000150, "b": 30000147, "y2": "504.5", "x2": "578.5", "y1": "539.5", "x1": "533.5", "type": "j"}, {"a": 30000149, "b": 30000148, "y2": "424.5", "x2": "483.5", "y1": "464.5", "x1": "468.5", "type": "j"}, {"a": 30000152, "b": 30000148, "y2": "459.5", "x2": "553.5", "y1": "464.5", "x1": "468.5", "type": "j"}, {"a": 30000151, "b": 30000149, "y2": "374.5", "x2": "503.5", "y1": "424.5", "x1": "483.5", "type": "j"}, {"a": 30000152, "b": 30000150, "y2": "459.5", "x2": "553.5", "y1": "504.5", "x1": "578.5", "type": "j"}, {"a": 30000173, "b": 30000151, "y2": "274.5", "x2": "563.5", "y1": "374.5", "x1": "503.5", "type": "jc"}, {"a": 30000159, "b": 30000152, "y2": "509.5", "x2": "708.5", "y1": "459.5", "x1": "553.5", "type": "jc"}, {"a": 30000154, "b": 30000153, "y2": "329.5", "x2": "678.5", "y1": "404.5", "x1": "703.5", "type": "j"}, {"a": 30000155, "b": 30000153, "y2": "359.5", "x2": "748.5", "y1": "404.5", "x1": "703.5", "type": "j"}, {"a": 30000156, "b": 30000153, "y2": "308.5", "x2": "602.5", "y1": "404.5", "x1": "703.5", "type": "j"}, {"a": 30000157, "b": 30000153, "y2": "384.5", "x2": "623.5", "y1": "404.5", "x1": "703.5", "type": "j"}, {"a": 30000155, "b": 30000154, "y2": "359.5", "x2": "748.5", "y1": "329.5", "x1": "678.5", "type": "j"}, {"a": 30000156, "b": 30000154, "y2": "308.5", "x2": "602.5", "y1": "329.5", "x1": "678.5", "type": "j"}, {"a": 30000158, "b": 30000155, "y2": "349.5", "x2": "813.5", "y1": "359.5", "x1": "748.5", "type": "j"}, {"a": 30000157, "b": 30000156, "y2": "384.5", "x2": "623.5", "y1": "308.5", "x1": "602.5", "type": "j"}, {"a": 30000165, "b": 30000158, "y2": "294.5", "x2": "813.5", "y1": "349.5", "x1": "813.5", "type": "jc"}, {"a": 30000180, "b": 30000158, "y2": "404.5", "x2": "833.5", "y1": "349.5", "x1": "813.5", "type": "jc"}, {"a": 30000160, "b": 30000159, "y2": "529.5", "x2": "768.5", "y1": "509.5", "x1": "708.5", "type": "j"}, {"a": 30000161, "b": 30000159, "y2": "549.5", "x2": "698.5", "y1": "509.5", "x1": "708.5", "type": "j"}, {"a": 30000161, "b": 30000160, "y2": "549.5", "x2": "698.5", "y1": "529.5", "x1": "768.5", "type": "j"}, {"a": 30000163, "b": 30000160, "y2": "579.5", "x2": "823.5", "y1": "529.5", "x1": "768.5", "type": "j"}, {"a": 30000162, "b": 30000161, "y2": "589.5", "x2": "733.5", "y1": "549.5", "x1": "698.5", "type": "j"}, {"a": 30000163, "b": 30000162, "y2": "579.5", "x2": "823.5", "y1": "589.5", "x1": "733.5", "type": "j"}, {"a": 30000164, "b": 30000163, "y2": "614.5", "x2": "808.5", "y1": "579.5", "x1": "823.5", "type": "j"}, {"a": 30000186, "b": 30000163, "y2": "524.5", "x2": "838.5", "y1": "579.5", "x1": "823.5", "type": "jc"}, {"a": 30000195, "b": 30000164, "y2": "649.5", "x2": "773.5", "y1": "614.5", "x1": "808.5", "type": "jc"}, {"a": 30000166, "b": 30000165, "y2": "249.5", "x2": "783.5", "y1": "294.5", "x1": "813.5", "type": "j"}, {"a": 30000167, "b": 30000165, "y2": "244.5", "x2": "858.5", "y1": "294.5", "x1": "813.5", "type": "j"}, {"a": 30000167, "b": 30000166, "y2": "244.5", "x2": "858.5", "y1": "249.5", "x1": "783.5", "type": "j"}, {"a": 30000168, "b": 30000166, "y2": "199.5", "x2": "813.5", "y1": "249.5", "x1": "783.5", "type": "j"}, {"a": 30000168, "b": 30000167, "y2": "199.5", "x2": "813.5", "y1": "244.5", "x1": "858.5", "type": "j"}, {"a": 30000170, "b": 30000167, "y2": "234.5", "x2": "928.5", "y1": "244.5", "x1": "858.5", "type": "j"}, {"a": 30000169, "b": 30000168, "y2": "149.5", "x2": "798.5", "y1": "199.5", "x1": "813.5", "type": "j"}, {"a": 30000171, "b": 30000168, "y2": "149.5", "x2": "903.5", "y1": "199.5", "x1": "813.5", "type": "j"}, {"a": 30000171, "b": 30000169, "y2": "149.5", "x2": "903.5", "y1": "149.5", "x1": "798.5", "type": "j"}, {"a": 30000172, "b": 30000169, "y2": "109.5", "x2": "863.5", "y1": "149.5", "x1": "798.5", "type": "j"}, {"a": 30000194, "b": 30000169, "y2": "114.5", "x2": "678.5", "y1": "149.5", "x1": "798.5", "type": "jc"}, {"a": 30000174, "b": 30000173, "y2": "234.5", "x2": "498.5", "y1": "274.5", "x1": "563.5", "type": "j"}, {"a": 30000175, "b": 30000173, "y2": "264.5", "x2": "643.5", "y1": "274.5", "x1": "563.5", "type": "j"}, {"a": 30000178, "b": 30000173, "y2": "234.5", "x2": "578.5", "y1": "274.5", "x1": "563.5", "type": "j"}, {"a": 30000176, "b": 30000174, "y2": "214.5", "x2": "428.5", "y1": "234.5", "x1": "498.5", "type": "j"}, {"a": 30000178, "b": 30000174, "y2": "234.5", "x2": "578.5", "y1": "234.5", "x1": "498.5", "type": "j"}, {"a": 30000178, "b": 30000175, "y2": "234.5", "x2": "578.5", "y1": "264.5", "x1": "643.5", "type": "j"}, {"a": 30000179, "b": 30000175, "y2": "279.5", "x2": "713.5", "y1": "264.5", "x1": "643.5", "type": "j"}, {"a": 30000177, "b": 30000176, "y2": "194.5", "x2": "358.5", "y1": "214.5", "x1": "428.5", "type": "j"}, {"a": 30000188, "b": 30000178, "y2": "184.5", "x2": "593.5", "y1": "234.5", "x1": "578.5", "type": "jc"}, {"a": 30000181, "b": 30000180, "y2": "449.5", "x2": "838.5", "y1": "404.5", "x1": "833.5", "type": "j"}, {"a": 30000182, "b": 30000180, "y2": "364.5", "x2": "883.5", "y1": "404.5", "x1": "833.5", "type": "j"}, {"a": 30000183, "b": 30000181, "y2": "444.5", "x2": "898.5", "y1": "449.5", "x1": "838.5", "type": "j"}, {"a": 30000185, "b": 30000181, "y2": "484.5", "x2": "838.5", "y1": "449.5", "x1": "838.5", "type": "j"}, {"a": 30000184, "b": 30000182, "y2": "369.5", "x2": "948.5", "y1": "364.5", "x1": "883.5", "type": "j"}, {"a": 30000187, "b": 30000182, "y2": "329.5", "x2": "913.5", "y1": "364.5", "x1": "883.5", "type": "j"}, {"a": 30000186, "b": 30000185, "y2": "524.5", "x2": "838.5", "y1": "484.5", "x1": "838.5", "type": "j"}, {"a": 30002440, "b": 30000186, "y2": "529.5", "x2": "918.5", "y1": "524.5", "x1": "838.5", "type": "jr"}, {"a": 30000189, "b": 30000188, "y2": "144.5", "x2": "593.5", "y1": "184.5", "x1": "593.5", "type": "j"}, {"a": 30000194, "b": 30000188, "y2": "114.5", "x2": "678.5", "y1": "184.5", "x1": "593.5", "type": "j"}, {"a": 30000190, "b": 30000189, "y2": "114.5", "x2": "513.5", "y1": "144.5", "x1": "593.5", "type": "j"}, {"a": 30000191, "b": 30000189, "y2": "89.5", "x2": "593.5", "y1": "144.5", "x1": "593.5", "type": "j"}, {"a": 30000194, "b": 30000189, "y2": "114.5", "x2": "678.5", "y1": "144.5", "x1": "593.5", "type": "j"}, {"a": 30000191, "b": 30000190, "y2": "89.5", "x2": "593.5", "y1": "114.5", "x1": "513.5", "type": "j"}, {"a": 30000192, "b": 30000190, "y2": "54.5", "x2": "593.5", "y1": "114.5", "x1": "513.5", "type": "j"}, {"a": 30000193, "b": 30000190, "y2": "109.5", "x2": "438.5", "y1": "114.5", "x1": "513.5", "type": "j"}, {"a": 30000194, "b": 30000190, "y2": "114.5", "x2": "678.5", "y1": "114.5", "x1": "513.5", "type": "j"}, {"a": 30000192, "b": 30000191, "y2": "54.5", "x2": "593.5", "y1": "89.5", "x1": "593.5", "type": "j"}, {"a": 30000194, "b": 30000191, "y2": "114.5", "x2": "678.5", "y1": "89.5", "x1": "593.5", "type": "j"}, {"a": 30000193, "b": 30000192, "y2": "109.5", "x2": "438.5", "y1": "54.5", "x1": "593.5", "type": "j"}, {"a": 30000194, "b": 30000192, "y2": "114.5", "x2": "678.5", "y1": "54.5", "x1": "593.5", "type": "j"}, {"a": 30000207, "b": 30000192, "y2": "54.5", "x2": "428.5", "y1": "54.5", "x1": "593.5", "type": "jc"}, {"a": 30000201, "b": 30000193, "y2": "109.5", "x2": "328.5", "y1": "109.5", "x1": "438.5", "type": "jc"}, {"a": 30000196, "b": 30000195, "y2": "674.5", "x2": "708.5", "y1": "649.5", "x1": "773.5", "type": "j"}, {"a": 30000197, "b": 30000196, "y2": "704.5", "x2": "758.5", "y1": "674.5", "x1": "708.5", "type": "j"}, {"a": 30000200, "b": 30000196, "y2": "679.5", "x2": "623.5", "y1": "674.5", "x1": "708.5", "type": "j"}, {"a": 30000198, "b": 30000197, "y2": "719.5", "x2": "683.5", "y1": "704.5", "x1": "758.5", "type": "j"}, {"a": 30000199, "b": 30000197, "y2": "719.5", "x2": "828.5", "y1": "704.5", "x1": "758.5", "type": "j"}, {"a": 30002355, "b": 30000198, "y2": "754.5", "x2": "683.5", "y1": "719.5", "x1": "683.5", "type": "jr"}, {"a": 30003446, "b": 30000199, "y2": "754.5", "x2": "828.5", "y1": "719.5", "x1": "828.5", "type": "jr"}, {"a": 30002062, "b": 30000200, "y2": "709.5", "x2": "563.5", "y1": "679.5", "x1": "623.5", "type": "jr"}, {"a": 30002475, "b": 30000200, "y2": "664.5", "x2": "563.5", "y1": "679.5", "x1": "623.5", "type": "jr"}, {"a": 30000202, "b": 30000201, "y2": "54.5", "x2": "328.5", "y1": "109.5", "x1": "328.5", "type": "j"}, {"a": 30000206, "b": 30000201, "y2": "109.5", "x2": "253.5", "y1": "109.5", "x1": "328.5", "type": "j"}, {"a": 30000203, "b": 30000202, "y2": "19.5", "x2": "383.5", "y1": "54.5", "x1": "328.5", "type": "j"}, {"a": 30000204, "b": 30000202, "y2": "54.5", "x2": "253.5", "y1": "54.5", "x1": "328.5", "type": "j"}, {"a": 30000207, "b": 30000202, "y2": "54.5", "x2": "428.5", "y1": "54.5", "x1": "328.5", "type": "j"}, {"a": 30000207, "b": 30000203, "y2": "54.5", "x2": "428.5", "y1": "19.5", "x1": "383.5", "type": "j"}, {"a": 30000205, "b": 30000204, "y2": "54.5", "x2": "178.5", "y1": "54.5", "x1": "253.5", "type": "j"}, {"a": 30000250, "b": 30000205, "y2": "15.5", "x2": "179.5", "y1": "54.5", "x1": "178.5", "type": "jr"}, {"a": 30001448, "b": 30000205, "y2": "53.5", "x2": "110.5", "y1": "54.5", "x1": "178.5", "type": "jr"}, {"a": 30001393, "b": 30001363, "y2": "314.5", "x2": "330.5", "y1": "349.5", "x1": "334.5", "type": "jc"}, {"a": 30002791, "b": 30002788, "y2": "604.5", "x2": "73.5", "y1": "679.5", "x1": "128.5", "type": "j"}], "bridges": [], "systems": [{"name": "Outuni", "hasStation": true, "region": "", "y": "145", "x": "0", "id": 30000135}, {"name": "Sakenta", "hasStation": true, "region": "", "y": "290", "x": "0", "id": 30010141}, {"name": "Eskunen", "hasStation": true, "region": "", "y": "100", "x": "35", "id": 30000137}, {"name": "Hykkota", "hasStation": true, "region": "", "y": "190", "x": "45", "id": 30000134}, {"name": "Ansila", "hasStation": true, "region": "", "y": "229", "x": "66", "id": 30000132}, {"name": "Ohmahailen", "hasStation": true, "region": "", "y": "145", "x": "80", "id": 30000136}, {"name": "Ikuchi", "hasStation": true, "region": "", "y": "272", "x": "94", "id": 30000138}, {"name": "Urlen", "hasStation": true, "region": "", "y": "490", "x": "95", "id": 30000139}, {"name": "Hirtamon", "hasStation": true, "region": "", "y": "243", "x": "134", "id": 30000133}, {"name": "Unpas", "hasStation": true, "region": "", "y": "575", "x": "135", "id": 30000129}, {"name": "Aokannitoh", "hasStation": true, "region": "", "y": "205", "x": "145", "id": 30021407}, {"name": "Perimeter", "hasStation": true, "region": "", "y": "380", "x": "146", "id": 30000144}, {"name": "Niyabainen", "hasStation": true, "region": "", "y": "327", "x": "147", "id": 30000143}, {"name": "Obe", "hasStation": true, "region": "", "y": "40", "x": "150", "id": 30000205}, {"name": "Kisogo", "hasStation": true, "region": "", "y": "480", "x": "160", "id": 30000141}, {"name": "Uitra", "hasStation": true, "region": "", "y": "545", "x": "200", "id": 30030141}, {"name": "Shihuken", "hasStation": true, "region": "", "y": "620", "x": "200", "id": 30000130}, {"name": "Jita", "hasStation": true, "region": "", "y": "343", "x": "224", "id": 30000142}, {"name": "Ohkunen", "hasStation": true, "region": "", "y": "40", "x": "225", "id": 30000204}, {"name": "Wirashoda", "hasStation": true, "region": "", "y": "95", "x": "225", "id": 30000206}, {"name": "New Caldari", "hasStation": true, "region": "", "y": "279", "x": "225", "id": 30000145}, {"name": "Maurasi", "hasStation": true, "region": "", "y": "403", "x": "226", "id": 30000140}, {"name": "Jatate", "hasStation": true, "region": "", "y": "445", "x": "240", "id": 30000121}, {"name": "Vaankalen", "hasStation": true, "region": "", "y": "480", "x": "265", "id": 30000123}, {"name": "Senda", "hasStation": true, "region": "", "y": "580", "x": "265", "id": 30020141}, {"name": "Sirseshin", "hasStation": true, "region": "", "y": "675", "x": "265", "id": 30000127}, {"name": "Mastakomon", "hasStation": true, "region": "", "y": "40", "x": "300", "id": 30000202}, {"name": "Uchoshi", "hasStation": true, "region": "", "y": "95", "x": "300", "id": 30000201}, {"name": "Itamo", "hasStation": true, "region": "", "y": "445", "x": "305", "id": 30000119}, {"name": "Tuuriainas", "hasStation": true, "region": "", "y": "640", "x": "305", "id": 30000128}, {"name": "Ukkalen", "hasStation": true, "region": "", "y": "180", "x": "330", "id": 30000177}, {"name": "Mitsolen", "hasStation": true, "region": "", "y": "485", "x": "335", "id": 30000120}, {"name": "Eruka", "hasStation": true, "region": "", "y": "5", "x": "355", "id": 30000203}, {"name": "Kylmabe", "hasStation": false, "region": "", "y": "415", "x": "355", "id": 30000124}, {"name": "Mahtista", "hasStation": false, "region": "", "y": "520", "x": "360", "id": 30000122}, {"name": "Ahtulaima", "hasStation": false, "region": "", "y": "455", "x": "370", "id": 30000125}, {"name": "Osaa", "hasStation": true, "region": "", "y": "40", "x": "400", "id": 30000207}, {"name": "Keikaken", "hasStation": true, "region": "", "y": "200", "x": "400", "id": 30000176}, {"name": "Vouskiaho", "hasStation": true, "region": "", "y": "95", "x": "410", "id": 30000193}, {"name": "Geras", "hasStation": true, "region": "", "y": "645", "x": "410", "id": 30000126}, {"name": "Jakanerva", "hasStation": true, "region": "", "y": "450", "x": "440", "id": 30000148}, {"name": "Saisio", "hasStation": true, "region": "", "y": "500", "x": "445", "id": 30000146}, {"name": "Gekutami", "hasStation": true, "region": "", "y": "410", "x": "455", "id": 30000149}, {"name": "Onuse", "hasStation": true, "region": "", "y": "220", "x": "470", "id": 30000174}, {"name": "Uoyonen", "hasStation": true, "region": "", "y": "360", "x": "475", "id": 30000151}, {"name": "Vasala", "hasStation": true, "region": "", "y": "100", "x": "485", "id": 30000190}, {"name": "Nomaa", "hasStation": true, "region": "", "y": "620", "x": "485", "id": 30000131}, {"name": "Abagawa", "hasStation": true, "region": "", "y": "525", "x": "505", "id": 30000147}, {"name": "Hampinen", "hasStation": true, "region": "", "y": "445", "x": "525", "id": 30000152}, {"name": "Vattuolen", "hasStation": true, "region": "", "y": "260", "x": "535", "id": 30000173}, {"name": "Akkilen", "hasStation": true, "region": "", "y": "220", "x": "550", "id": 30000178}, {"name": "Hurtoken", "hasStation": true, "region": "", "y": "490", "x": "550", "id": 30000150}, {"name": "Otanuomi", "hasStation": true, "region": "", "y": "40", "x": "565", "id": 30000192}, {"name": "Walvalin", "hasStation": false, "region": "", "y": "75", "x": "565", "id": 30000191}, {"name": "Kiainti", "hasStation": true, "region": "", "y": "130", "x": "565", "id": 30000189}, {"name": "Hentogaira", "hasStation": true, "region": "", "y": "170", "x": "565", "id": 30000188}, {"name": "Josameto", "hasStation": true, "region": "", "y": "294", "x": "574", "id": 30000156}, {"name": "Otela", "hasStation": true, "region": "", "y": "370", "x": "595", "id": 30000157}, {"name": "Akkio", "hasStation": true, "region": "", "y": "665", "x": "595", "id": 30000200}, {"name": "Soshin", "hasStation": true, "region": "", "y": "250", "x": "615", "id": 30000175}, {"name": "Otsela", "hasStation": true, "region": "", "y": "100", "x": "650", "id": 30000194}, {"name": "Liekuri", "hasStation": true, "region": "", "y": "315", "x": "650", "id": 30000154}, {"name": "Paala", "hasStation": false, "region": "", "y": "705", "x": "655", "id": 30000198}, {"name": "Purjola", "hasStation": true, "region": "", "y": "535", "x": "670", "id": 30000161}, {"name": "Poinen", "hasStation": true, "region": "", "y": "390", "x": "675", "id": 30000153}, {"name": "Ikami", "hasStation": true, "region": "", "y": "495", "x": "680", "id": 30000159}, {"name": "Otosela", "hasStation": true, "region": "", "y": "660", "x": "680", "id": 30000196}, {"name": "Silen", "hasStation": true, "region": "", "y": "265", "x": "685", "id": 30000179}, {"name": "Maila", "hasStation": true, "region": "", "y": "575", "x": "705", "id": 30000162}, {"name": "Obanen", "hasStation": false, "region": "", "y": "345", "x": "720", "id": 30000155}, {"name": "Uemon", "hasStation": true, "region": "", "y": "690", "x": "730", "id": 30000197}, {"name": "Reisen", "hasStation": true, "region": "", "y": "515", "x": "740", "id": 30000160}, {"name": "Tasti", "hasStation": true, "region": "", "y": "635", "x": "745", "id": 30000195}, {"name": "Airmia", "hasStation": false, "region": "", "y": "235", "x": "755", "id": 30000166}, {"name": "Ihakana", "hasStation": true, "region": "", "y": "135", "x": "770", "id": 30000169}, {"name": "Messoya", "hasStation": true, "region": "", "y": "600", "x": "780", "id": 30000164}, {"name": "Friggi", "hasStation": true, "region": "", "y": "185", "x": "785", "id": 30000168}, {"name": "Ishisomo", "hasStation": true, "region": "", "y": "280", "x": "785", "id": 30000165}, {"name": "Olo", "hasStation": true, "region": "", "y": "335", "x": "785", "id": 30000158}, {"name": "Akora", "hasStation": true, "region": "", "y": "565", "x": "795", "id": 30000163}, {"name": "Fuskunen", "hasStation": false, "region": "", "y": "705", "x": "800", "id": 30000199}, {"name": "Osmon", "hasStation": true, "region": "", "y": "390", "x": "805", "id": 30000180}, {"name": "Korsiki", "hasStation": true, "region": "", "y": "435", "x": "810", "id": 30000181}, {"name": "Airaken", "hasStation": true, "region": "", "y": "470", "x": "810", "id": 30000185}, {"name": "Oijanen", "hasStation": false, "region": "", "y": "510", "x": "810", "id": 30000186}, {"name": "Sakkikainen", "hasStation": true, "region": "", "y": "230", "x": "830", "id": 30000167}, {"name": "Otomainen", "hasStation": false, "region": "", "y": "95", "x": "835", "id": 30000172}, {"name": "Inaya", "hasStation": true, "region": "", "y": "350", "x": "855", "id": 30000182}, {"name": "Nuken", "hasStation": true, "region": "", "y": "430", "x": "870", "id": 30000183}, {"name": "Otitoh", "hasStation": true, "region": "", "y": "135", "x": "875", "id": 30000171}, {"name": "Wuos", "hasStation": true, "region": "", "y": "315", "x": "885", "id": 30000187}, {"name": "Vahunomi", "hasStation": true, "region": "", "y": "220", "x": "900", "id": 30000170}, {"name": "Uminas", "hasStation": true, "region": "", "y": "355", "x": "920", "id": 30000184}, {"name": "Kusomonmon", "hasStation": true, "region": "The Citadel", "y": "465", "x": "25", "id": 30002802}, {"name": "Iyen-Oursta", "hasStation": true, "region": "Sinq Laison", "y": "395", "x": "35", "id": 30002642}, {"name": "Sirppala", "hasStation": true, "region": "The Citadel", "y": "590", "x": "45", "id": 30002791}, {"name": "Tunttaras", "hasStation": true, "region": "Lonetrek", "y": "335", "x": "60", "id": 30001379}, {"name": "Hakonen", "hasStation": true, "region": "Lonetrek", "y": "39", "x": "82", "id": 30001448}, {"name": "Inaro", "hasStation": true, "region": "The Citadel", "y": "665", "x": "100", "id": 30002788}, {"name": "P3EN-E", "hasStation": false, "region": "Vale of the Silent", "y": "1", "x": "151", "id": 30000250}, {"name": "Malkalen", "hasStation": true, "region": "Lonetrek", "y": "300", "x": "302", "id": 30001393}, {"name": "Muvolailen", "hasStation": true, "region": "The Citadel", "y": "375", "x": "304", "id": 30002780}, {"name": "Alikara", "hasStation": true, "region": "The Citadel", "y": "235", "x": "305", "id": 30002754}, {"name": "Sobaseki", "hasStation": true, "region": "Lonetrek", "y": "335", "x": "306", "id": 30001363}, {"name": "EOA-ZC", "hasStation": false, "region": "Geminate", "y": "650", "x": "535", "id": 30002475}, {"name": "Todifrauan", "hasStation": true, "region": "Metropolis", "y": "695", "x": "535", "id": 30002062}, {"name": "LXQ2-T", "hasStation": true, "region": "Etherium Reach", "y": "740", "x": "655", "id": 30002355}, {"name": "Ofage", "hasStation": false, "region": "Metropolis", "y": "740", "x": "800", "id": 30003446}, {"name": "BWF-ZZ", "hasStation": true, "region": "Geminate", "y": "515", "x": "890", "id": 30002440}]}}